sa_filters/__init__.py
sa_filters/exceptions.py
sa_filters/filters.py
sa_filters/loads.py
sa_filters/models.py
sa_filters/pagination.py
sa_filters/sorting.py
sa_filters-2.1.0.dist-info/licenses/LICENSE
sa_filters-2.1.0.dist-info/METADATA
sa_filters-2.1.0.dist-info/WHEEL
sa_filters-2.1.0.dist-info/top_level.txt
sa_filters-2.1.0.dist-info/zip-safe
sa_filters-2.1.0.dist-info/RECORD
