Metadata-Version: 2.4
Name: sa-filters
Version: 2.1.0
Summary: A library to filter SQLAlchemy queries.
Author-email: "Student.com" <wearehiring@student.com>
Maintainer-email: slymit <slymit@gmail.com>
License-Expression: Apache-2.0
Project-URL: Homepage, https://github.com/slymit/sa-filters
Classifier: Intended Audience :: Developers
Classifier: Operating System :: OS Independent
Classifier: Programming Language :: Python
Classifier: Programming Language :: Python :: 3
Classifier: Programming Language :: Python :: 3.7
Classifier: Programming Language :: Python :: 3.8
Classifier: Programming Language :: Python :: 3.9
Classifier: Programming Language :: Python :: 3.10
Classifier: Programming Language :: Python :: 3.11
Classifier: Programming Language :: Python :: 3.12
Classifier: Programming Language :: Python :: 3.13
Classifier: Programming Language :: Python :: 3.14
Classifier: Topic :: Database
Classifier: Topic :: Database :: Front-Ends
Classifier: Topic :: Software Development :: Libraries :: Python Modules
Requires-Python: >=3.7
License-File: LICENSE
Requires-Dist: sqlalchemy>=1.4.24
Provides-Extra: dev
Requires-Dist: pytest>=6.2.5; extra == "dev"
Requires-Dist: packaging>=23.1; extra == "dev"
Requires-Dist: coverage>=7.0.0; extra == "dev"
Requires-Dist: sqlalchemy-utils~=0.41.1; extra == "dev"
Requires-Dist: flake8; extra == "dev"
Requires-Dist: restructuredtext-lint; extra == "dev"
Requires-Dist: Pygments; extra == "dev"
Provides-Extra: mysql
Requires-Dist: mysql-connector-python-rf==2.2.2; extra == "mysql"
Provides-Extra: postgresql
Requires-Dist: psycopg2~=2.9.9; extra == "postgresql"
Dynamic: license-file
